mehrlist/README.MD
mehrlist/__init__.py
mehrlist/requirements.txt
mehrlist/thirdparty.json
mehrlist-0.10.dist-info/LICENSE.rst
mehrlist-0.10.dist-info/METADATA
mehrlist-0.10.dist-info/WHEEL
mehrlist-0.10.dist-info/top_level.txt
mehrlist-0.10.dist-info/RECORD
