Metadata-Version: 2.1
Name: mehrlist
Version: 0.10
Summary: Subclass of list with more than 100 useful methods - pure Python
Home-page: https://github.com/hansalemaos/mehrlist
Author: Johannes Fischer
Author-email: aulasparticularesdealemaosp@gmail.com
License: MIT
Keywords: nested,list
Classifier: Development Status :: 4 - Beta
Classifier: Programming Language :: Python :: 3 :: Only
Classifier: Programming Language :: Python :: 3.10
Classifier: Topic :: Software Development :: Libraries :: Python Modules
Classifier: Topic :: Utilities
License-File: LICENSE.rst
Requires-Dist: bisectsearch
Requires-Dist: catmapper
Requires-Dist: flatten-any-dict-iterable-or-whatsoever
Requires-Dist: flatten-everything
Requires-Dist: intersection-grouper
Requires-Dist: isiter
Requires-Dist: levelflatten
Requires-Dist: list2tree
Requires-Dist: nested2nested
Requires-Dist: screwhashesset
Requires-Dist: tolerant-isinstance
